ads_base/__init__.py
ads_base/ads_utils.py
ads_base/apply_model.py
ads_base/download_model.py
ads_base/download_tests.py
ads_base/integrity_test.py
ads_base/model_cards.py
ads_base/params.py
ads_base/postprocessing.py
ads_base/segment.py
ads_base/version.txt
ads_base/morphometrics/__init__.py
ads_base/morphometrics/compute_morphometrics.py
ads_base/morphometrics/launch_morphometrics_computation.py
ads_base/testing/__init__.py
ads_base/testing/launch_performance_metrics.py
ads_base/testing/segmentation_scoring.py
ads_base/visualization/__init__.py
ads_base/visualization/colorization.py
ads_base/visualization/merge_masks.py
ads_base/visualization/simulate_axons.py
ads_base-5.0.6.dist-info/LICENSE
ads_base-5.0.6.dist-info/METADATA
ads_base-5.0.6.dist-info/WHEEL
ads_base-5.0.6.dist-info/entry_points.txt
ads_base-5.0.6.dist-info/top_level.txt
ads_base-5.0.6.dist-info/RECORD
