Metadata-Version: 2.2
Name: ads_base
Version: 5.0.6
Summary: Python tool for automatic axon and myelin segmentation
Home-page: https://github.com/neuropoly/axondeepseg
Author: NeuroPoly Lab, Polytechnique Montreal
Author-email: neuropoly@googlegroups.com
License: MIT
Keywords: axon myelin segmentation microscopy
Classifier: Development Status :: 3 - Alpha
Classifier: License :: OSI Approved :: MIT License
Classifier: Programming Language :: Python :: 3.11
Requires-Python: >=3.11
License-File: LICENSE
Requires-Dist: numpy<2
Requires-Dist: scipy
Requires-Dist: scikit-image
Requires-Dist: tabulate
Requires-Dist: pandas
Requires-Dist: matplotlib
Requires-Dist: mpld3
Requires-Dist: tqdm
Requires-Dist: requests
Requires-Dist: pillow!=9.0.0
Requires-Dist: imageio>=2.28.0
Requires-Dist: pytest
Requires-Dist: pytest-cov
Requires-Dist: prettytable
Requires-Dist: jupyter
Requires-Dist: openpyxl
Requires-Dist: qtconsole<5.4.2
Requires-Dist: napari
Requires-Dist: acvl_utils!=0.2.1
Requires-Dist: nnunetv2==2.2.1
Requires-Dist: loguru
Requires-Dist: torch<2.4.0
Requires-Dist: pydicom<3
Requires-Dist: pygit2
Requires-Dist: pytest-qt
Dynamic: author
Dynamic: author-email
Dynamic: classifier
Dynamic: description
Dynamic: description-content-type
Dynamic: home-page
Dynamic: keywords
Dynamic: license
Dynamic: requires-dist
Dynamic: requires-python
Dynamic: summary
